attabox/__init__.py
attabox/helloworld.py
attabox-0.1.2.dist-info/METADATA
attabox-0.1.2.dist-info/WHEEL
attabox-0.1.2.dist-info/top_level.txt
attabox-0.1.2.dist-info/RECORD
